{
  "type": "FeatureCollection",
  "features": [
    {
      "type": "Feature",
      "properties": {"id": "pl_1", "name": "Платон", "radius_m": 300, "note": "пример"},
      "geometry": {"type": "Point", "coordinates": [37.64, 55.76]}
    }
  ]
}